BRImage/__init__.py
BRImage/__main__.py
BRImage/glitchimage.py
BRImage/logging.py
BRImage/clib/__init__.py
BRImage/clib/_algorithms.cpython-38-darwin.so
BRImage/clib/algorithms.py
BRImage/commandline/__init__.py
BRImage/commandline/base_parser.py
BRImage/commandline/fm.py
BRImage/commandline/image_algorithms.py
BRImage/commandline/random_walk.py
BRImage/glitchcore/__init__.py
BRImage/glitchcore/helper.py
BRImage/glitchcore/image.py
BRImage/glitchcore/overlaybase.py
BRImage/overlays/__init__.py
BRImage/overlays/fm.py
BRImage/overlays/randomwalk.py
BRImage-0.1.9.dist-info/LICENSE
BRImage-0.1.9.dist-info/METADATA
BRImage-0.1.9.dist-info/WHEEL
BRImage-0.1.9.dist-info/entry_points.txt
BRImage-0.1.9.dist-info/top_level.txt
BRImage-0.1.9.dist-info/RECORD
