Metadata-Version: 2.1
Name: BRImage
Version: 0.1.9
Summary: Glitch Art Toolkit mimicking CRT monitor defects.
Home-page: https://github.com/Dustpancake/BRImage
Author: Dustpancake
License: UNKNOWN
Platform: UNKNOWN
Classifier: Programming Language :: Python :: 3.7
Classifier: License :: OSI Approved :: MIT License
Classifier: License :: OSI Approved :: GNU General Public License v3 (GPLv3)
Requires-Python: >=3.7
Requires-Dist: numpy (>=1.18.2)
Requires-Dist: scipy (>=1.4.1)
Requires-Dist: Pillow (>=7.1.1)
Requires-Dist: wheel (>=0.34.2)
Requires-Dist: setuptools (>=46.1.3)
